{
  "Courses": [{
    "id": "165075690003",
    "name": "Service Learning Grade 12",
    "descriptionHeading": "Service Learning Grade 12",
    "room": "103",
    "ownerId": "111035948671457692633",
    "creationTime": "2020-11-03T01:31:14.680Z",
    "updateTime": "2020-11-03T01:31:10.223Z",
    "courseState": "ACTIVE",
    "alternateLink": "https://classroom.google.com/c/MTY1MDc1NjkwMDAz",
    "teacherGroupEmail": "Service_Learning_Grade_12_teachers_be5562d3@classroom.google.com",
    "courseGroupEmail": "Service_Learning_Grade_12_dbdad49e@classroom.google.com",
    "guardiansEnabled": false,
    "calendarId": "classroom107750668568841940784@group.calendar.google.com"
  }, {
    "id": "169396614913",
    "name": "Grade 12 Elective Visual Arts",
    "section": "Friday 13:45",
    "descriptionHeading": "Grade 12 Elective Visual Arts Friday 13:45",
    "ownerId": "112885716356426487885",
    "creationTime": "2020-09-18T06:51:48.860Z",
    "updateTime": "2020-09-18T06:51:48.040Z",
    "courseState": "ACTIVE",
    "alternateLink": "https://classroom.google.com/c/MTY5Mzk2NjE0OTEz",
    "teacherGroupEmail": "Grade_12_Elective_Visual_Arts_Friday_13_45_teachers_80878708@classroom.google.com",
    "courseGroupEmail": "Grade_12_Elective_Visual_Arts_Friday_13_45_90887b38@classroom.google.com",
    "guardiansEnabled": false,
    "calendarId": "classroom109930929368786253222@group.calendar.google.com"
  }, {
    "id": "145659196942",
    "name": "PKN - GRADE 12",
    "section": "https://meet.google.com/qek-jnbo-wms",
    "descriptionHeading": "GRADE 12",
    "ownerId": "105675112725304498653",
    "creationTime": "2020-09-21T01:16:38.047Z",
    "updateTime": "2020-09-21T01:17:10.483Z",
    "courseState": "ACTIVE",
    "alternateLink": "https://classroom.google.com/c/MTQ1NjU5MTk2OTQy",
    "teacherGroupEmail": "GRADE_12_guru_6a3100c8@classroom.google.com",
    "courseGroupEmail": "GRADE_12_91a3ec7a@classroom.google.com",
    "guardiansEnabled": false,
    "calendarId": "classroom114846300178495014020@group.calendar.google.com"
  }, {
    "id": "163293041256",
    "name": "English B SL (Grade 12)",
    "section": "https://meet.google.com/zsa-phfp-qgk",
    "descriptionHeading": "English B SL (Grade 12)",
    "room": "305",
    "ownerId": "106758342862829267214",
    "creationTime": "2020-09-10T02:57:34.386Z",
    "updateTime": "2020-09-16T03:08:33.967Z",
    "courseState": "ACTIVE",
    "alternateLink": "https://classroom.google.com/c/MTYzMjkzMDQxMjU2",
    "teacherGroupEmail": "English_B_SL_Grade_12_teachers_d5fa8ad9@classroom.google.com",
    "courseGroupEmail": "English_B_SL_Grade_12_52a17836@classroom.google.com",
    "guardiansEnabled": false,
    "calendarId": "classroom114834301912660379043@group.calendar.google.com"
  }, {
    "id": "163249867175",
    "name": "Counseling 12",
    "section": "https://meet.google.com/uxd-wwpr-ggf",
    "descriptionHeading": "Counseling 12",
    "ownerId": "103837806259058468984",
    "creationTime": "2020-09-10T01:14:22.558Z",
    "updateTime": "2020-09-13T12:47:35.223Z",
    "courseState": "ACTIVE",
    "alternateLink": "https://classroom.google.com/c/MTYzMjQ5ODY3MTc1",
    "teacherGroupEmail": "Counseling_12_guru_a1dbd085@classroom.google.com",
    "courseGroupEmail": "Counseling_12_e5598075@classroom.google.com",
    "guardiansEnabled": false,
    "calendarId": "classroom101379440259561130478@group.calendar.google.com"
  }, {
    "id": "164694559445",
    "name": "PPS G12 20202021",
    "section": "https://meet.google.com/dav-kzcq-nrh",
    "descriptionHeading": "PPS G12 20202021 https://meet.google.com/dav-kzcq-nrh",
    "ownerId": "109876031239742970399",
    "creationTime": "2020-09-15T01:59:04.989Z",
    "updateTime": "2020-09-15T01:59:04.185Z",
    "courseState": "ACTIVE",
    "alternateLink": "https://classroom.google.com/c/MTY0Njk0NTU5NDQ1",
    "teacherGroupEmail": "PPS_G12_20202021_https_meet_google_com_dav_kzcq_nrh_teachers_3499b946@classroom.google.com",
    "courseGroupEmail": "PPS_G12_20202021_https_meet_google_com_dav_kzcq_nrh_17034275@classroom.google.com",
    "guardiansEnabled": false,
    "calendarId": "classroom115699249925059939645@group.calendar.google.com"
  }, {
    "id": "163338843667",
    "name": "PHE G12 - https://meet.google.com/dms-cdod-ixa",
    "section": "Tuesday (08.30 - 10.00)",
    "descriptionHeading": "PHE G12 CP",
    "room": "Mainhall",
    "ownerId": "116449479320330635207",
    "creationTime": "2020-09-10T06:50:12.786Z",
    "updateTime": "2020-10-13T22:44:31.133Z",
    "courseState": "ACTIVE",
    "alternateLink": "https://classroom.google.com/c/MTYzMzM4ODQzNjY3",
    "teacherGroupEmail": "PHE_G12_CP_teachers_e22a03a3@classroom.google.com",
    "courseGroupEmail": "PHE_G12_CP_9c10cce8@classroom.google.com",
    "guardiansEnabled": false,
    "calendarId": "classroom108183698132946226997@group.calendar.google.com"
  }, {
    "id": "163269978144",
    "name": "Mathematics & Tutor Grade 12",
    "section": "https://meet.google.com/rmi-dfgc-kos",
    "descriptionHeading": "Mathematics & Tutor Grade 12",
    "ownerId": "112009295012956326180",
    "creationTime": "2020-09-10T01:46:07.273Z",
    "updateTime": "2020-09-14T01:28:35.456Z",
    "courseState": "ACTIVE",
    "alternateLink": "https://classroom.google.com/c/MTYzMjY5OTc4MTQ0",
    "teacherGroupEmail": "Mathematics_Tutor_Grade_12_guru_3bf3e093@classroom.google.com",
    "courseGroupEmail": "Mathematics_Tutor_Grade_12_bed6a090@classroom.google.com",
    "guardiansEnabled": false,
    "calendarId": "classroom103647781739461284669@group.calendar.google.com"
  }, {
    "id": "154593192134",
    "name": "Grade 12 Islamic Studies",
    "section": "https://meet.google.com/rbi-rsam-rkf",
    "descriptionHeading": "Grade 12 Islamic Studies IBCP",
    "description": "IBCP",
    "room": "105",
    "ownerId": "102795651699506546012",
    "creationTime": "2020-09-10T06:12:31.333Z",
    "updateTime": "2020-09-18T07:21:19.690Z",
    "courseState": "ACTIVE",
    "alternateLink": "https://classroom.google.com/c/MTU0NTkzMTkyMTM0",
    "teacherGroupEmail": "Grade_12_Islamic_Studies_IBCP_teachers_3b1bf7c6@classroom.google.com",
    "courseGroupEmail": "Grade_12_Islamic_Studies_IBCP_0ee08a61@classroom.google.com",
    "guardiansEnabled": false,
    "calendarId": "classroom116191381100666880018@group.calendar.google.com"
  }, {
    "id": "155054857075",
    "name": "LD German G12",
    "section": "https://meet.google.com/qnu-qwcn-ovi",
    "descriptionHeading": "LG German G12",
    "ownerId": "116503715439052063463",
    "creationTime": "2020-09-11T04:04:13.708Z",
    "updateTime": "2020-09-12T15:18:26.706Z",
    "courseState": "ACTIVE",
    "alternateLink": "https://classroom.google.com/c/MTU1MDU0ODU3MDc1",
    "teacherGroupEmail": "LG_German_G12_teachers_122b9c5f@classroom.google.com",
    "courseGroupEmail": "LG_German_G12_843991be@classroom.google.com",
    "guardiansEnabled": false,
    "calendarId": "classroom100134844320975562812@group.calendar.google.com"
  }, {
    "id": "163233439749",
    "name": "Physics 12",
    "section": "https://meet.google.com/xpk-qzrc-sqz",
    "descriptionHeading": "Physics 12 2020-2021",
    "description": "2020-2021",
    "ownerId": "102506228869865981637",
    "creationTime": "2020-09-09T23:06:06.044Z",
    "updateTime": "2020-10-13T02:28:54.166Z",
    "courseState": "ACTIVE",
    "alternateLink": "https://classroom.google.com/c/MTYzMjMzNDM5NzQ5",
    "teacherGroupEmail": "Physics_12_2020_2021_teachers_ddde7d4a@classroom.google.com",
    "courseGroupEmail": "Physics_12_2020_2021_5c20ae40@classroom.google.com",
    "guardiansEnabled": false,
    "calendarId": "classroom101502961090490067177@group.calendar.google.com"
  }, {
    "id": "144616106102",
    "name": "Chemistry",
    "section": "Grade 12 https://meet.google.com/kuy-aqad-hak",
    "descriptionHeading": "Chemistry Grade 12",
    "ownerId": "112180687494583628803",
    "creationTime": "2020-09-09T22:09:59.298Z",
    "updateTime": "2020-09-12T15:14:25.947Z",
    "courseState": "ACTIVE",
    "alternateLink": "https://classroom.google.com/c/MTQ0NjE2MTA2MTAy",
    "teacherGroupEmail": "Chemistry_Grade_12_teachers_43810a83@classroom.google.com",
    "courseGroupEmail": "Chemistry_Grade_12_2cb5d018@classroom.google.com",
    "guardiansEnabled": false,
    "calendarId": "classroom113392450100486594859@group.calendar.google.com"
  }, {
    "id": "163254674061",
    "name": "Career-related Studies (CRS) Grade 12",
    "section": "https://meet.google.com/nrs-hdkc-cbn",
    "descriptionHeading": "Career-related Studies (CRS) IBCP",
    "room": "104",
    "ownerId": "111035948671457692633",
    "creationTime": "2020-09-10T00:52:50.988Z",
    "updateTime": "2020-09-24T04:59:06.829Z",
    "courseState": "ACTIVE",
    "alternateLink": "https://classroom.google.com/c/MTYzMjU0Njc0MDYx",
    "teacherGroupEmail": "Career_related_Studies_CRS_IBCP_teachers_8e5f32f9@classroom.google.com",
    "courseGroupEmail": "Career_related_Studies_CRS_IBCP_d0e8f01b@classroom.google.com",
    "guardiansEnabled": false,
    "calendarId": "classroom101637392230297112439@group.calendar.google.com"
  }, {
    "id": "144617580190",
    "name": "Biology Grade 12",
    "section": "https://meet.google.com/dyq-bozi-uxu",
    "descriptionHeading": "Biology Grade 12 IBCP",
    "description": "IBCP",
    "room": "104",
    "ownerId": "111035948671457692633",
    "creationTime": "2020-09-09T22:28:31.910Z",
    "updateTime": "2020-09-15T06:56:57.494Z",
    "courseState": "ACTIVE",
    "alternateLink": "https://classroom.google.com/c/MTQ0NjE3NTgwMTkw",
    "teacherGroupEmail": "Biology_Grade_12_IBCP_teachers_1cd6272c@classroom.google.com",
    "courseGroupEmail": "Biology_Grade_12_IBCP_5c13f9be@classroom.google.com",
    "guardiansEnabled": false,
    "calendarId": "classroom106914878478072031299@group.calendar.google.com"
  }, {
    "id": "163263500108",
    "name": "G12 - Language Literature 2020/2021",
    "section": "Bahasa Indonesia",
    "descriptionHeading": "G12 - 2020/2021 Language Literature",
    "room": "BI - 12",
    "ownerId": "107645847065280922648",
    "creationTime": "2020-09-10T00:53:32.120Z",
    "updateTime": "2020-09-14T01:41:11.332Z",
    "courseState": "ACTIVE",
    "alternateLink": "https://classroom.google.com/c/MTYzMjYzNTAwMTA4",
    "teacherGroupEmail": "G12_2020_2021_Language_Literature_teachers_da0d6521@classroom.google.com",
    "courseGroupEmail": "G12_2020_2021_Language_Literature_c313d36a@classroom.google.com",
    "guardiansEnabled": false,
    "calendarId": "classroom116952542097760720971@group.calendar.google.com"
  }]
}